{"fonts/AvenirLTStd-Black.otf":["fonts/AvenirLTStd-Black.otf"],"fonts/AvenirLTStd-BlackOblique.otf":["fonts/AvenirLTStd-BlackOblique.otf"],"fonts/AvenirLTStd-Book.otf":["fonts/AvenirLTStd-Book.otf"],"fonts/AvenirLTStd-BookOblique.otf":["fonts/AvenirLTStd-BookOblique.otf"],"fonts/AvenirLTStd-Heavy.otf":["fonts/AvenirLTStd-Heavy.otf"],"fonts/AvenirLTStd-HeavyOblique.otf":["fonts/AvenirLTStd-HeavyOblique.otf"],"fonts/AvenirLTStd-Light.otf":["fonts/AvenirLTStd-Light.otf"],"fonts/AvenirLTStd-LightOblique.otf":["fonts/AvenirLTStd-LightOblique.otf"],"fonts/AvenirLTStd-Medium.otf":["fonts/AvenirLTStd-Medium.otf"],"fonts/AvenirLTStd-MediumOblique.otf":["fonts/AvenirLTStd-MediumOblique.otf"],"fonts/AvenirLTStd-Oblique.otf":["fonts/AvenirLTStd-Oblique.otf"],"fonts/AvenirLTStd-Roman.otf":["fonts/AvenirLTStd-Roman.otf"],"fonts/HelveticaNeue-Medium.otf":["fonts/HelveticaNeue-Medium.otf"],"assets/appBarTitle.png":["assets/appBarTitle.png"],"assets/barcode.png":["assets/barcode.png"],"assets/burlap.png":["assets/burlap.png"],"assets/burlapSm.png":["assets/burlapSm.png"],"assets/headerSmall.jpg":["assets/headerSmall.jpg"],"assets/siteIcon.png":["assets/siteIcon.png"],"assets/title.png":["assets/title.png"]}